{
    "TextDetections": [
        {
            "DetectedText": ".ings- -Zeiten",
            "Type": "LINE",
            "Id": 0,
            "Confidence": 89.30705261230469,
            "Geometry": {
                "BoundingBox": {
                    "Width": 0.2933533191680908,
                    "Height": 0.158971905708313,
                    "Left": 0.439146488904953,
                    "Top": 0.2921535074710846
                },
                "Polygon": [
                    {
                        "X": 0.4499388337135315,
                        "Y": 0.2921535074710846
                    },
                    {
                        "X": 0.7324998378753662,
                        "Y": 0.34183093905448914
                    },
                    {
                        "X": 0.7217074632644653,
                        "Y": 0.4511254131793976
                    },
                    {
                        "X": 0.439146488904953,
                        "Y": 0.40144795179367065
                    }
                ]
            }
        },
        {
            "DetectedText": "Montag bis Freitag 10.00-18.30 Uhr",
            "Type": "LINE",
            "Id": 1,
            "Confidence": 98.02177429199219,
            "Geometry": {
                "BoundingBox": {
                    "Width": 0.3403398096561432,
                    "Height": 0.06130848452448845,
                    "Left": 0.35033419728279114,
                    "Top": 0.47841086983680725
                },
                "Polygon": [
                    {
                        "X": 0.35189059376716614,
                        "Y": 0.47841086983680725
                    },
                    {
                        "X": 0.6906740069389343,
                        "Y": 0.508128821849823
                    },
                    {
                        "X": 0.6891176104545593,
                        "Y": 0.5397193431854248
                    },
                    {
                        "X": 0.35033419728279114,
                        "Y": 0.5100014209747314
                    }
                ]
            }
        },
        {
            "DetectedText": "Samstag 10.00 17.00 Uhr",
            "Type": "LINE",
            "Id": 2,
            "Confidence": 95.5758056640625,
            "Geometry": {
                "BoundingBox": {
                    "Width": 0.24187453091144562,
                    "Height": 0.05235712602734566,
                    "Left": 0.3959987163543701,
                    "Top": 0.5805805921554565
                },
                "Polygon": [
                    {
                        "X": 0.39759939908981323,
                        "Y": 0.5805805921554565
                    },
                    {
                        "X": 0.6378732323646545,
                        "Y": 0.6060125231742859
                    },
                    {
                        "X": 0.6362726092338562,
                        "Y": 0.6329377293586731
                    },
                    {
                        "X": 0.3959987163543701,
                        "Y": 0.6075057983398438
                    }
                ]
            }
        },
        {
            "DetectedText": ".ings-",
            "Type": "WORD",
            "Id": 3,
            "ParentId": 0,
            "Confidence": 85.43521881103516,
            "Geometry": {
                "BoundingBox": {
                    "Width": 0.13273626565933228,
                    "Height": 0.07641143351793289,
                    "Left": 0.4621155261993408,
                    "Top": 0.2942942976951599
                },
                "Polygon": [
                    {
                        "X": 0.4621155261993408,
                        "Y": 0.2942942976951599
                    },
                    {
                        "X": 0.5828956961631775,
                        "Y": 0.34934934973716736
                    },
                    {
                        "X": 0.564141035079956,
                        "Y": 0.4234234094619751
                    },
                    {
                        "X": 0.44261065125465393,
                        "Y": 0.36636635661125183
                    }
                ]
            }
        },
        {
            "DetectedText": "-Zeiten",
            "Type": "WORD",
            "Id": 4,
            "ParentId": 0,
            "Confidence": 93.17887878417969,
            "Geometry": {
                "BoundingBox": {
                    "Width": 0.1669742614030838,
                    "Height": 0.05813555419445038,
                    "Left": 0.5618904829025269,
                    "Top": 0.3433433473110199
                },
                "Polygon": [
                    {
                        "X": 0.5618904829025269,
                        "Y": 0.3433433473110199
                    },
                    {
                        "X": 0.7284321188926697,
                        "Y": 0.3553553521633148
                    },
                    {
                        "X": 0.7254313826560974,
                        "Y": 0.413413405418396
                    },
                    {
                        "X": 0.5596399307250977,
                        "Y": 0.4014014005661011
                    }
                ]
            }
        },
        {
            "DetectedText": "Montag",
            "Type": "WORD",
            "Id": 5,
            "ParentId": 1,
            "Confidence": 99.6963882446289,
            "Geometry": {
                "BoundingBox": {
                    "Width": 0.07451102137565613,
                    "Height": 0.03106728196144104,
                    "Left": 0.35183796286582947,
                    "Top": 0.47947949171066284
                },
                "Polygon": [
                    {
                        "X": 0.35183796286582947,
                        "Y": 0.47947949171066284
                    },
                    {
                        "X": 0.4261065125465393,
                        "Y": 0.4854854941368103
                    },
                    {
                        "X": 0.4246061444282532,
                        "Y": 0.5165165066719055
                    },
                    {
                        "X": 0.3510877788066864,
                        "Y": 0.5095095038414001
                    }
                ]
            }
        },
        {
            "DetectedText": "bis",
            "Type": "WORD",
            "Id": 6,
            "ParentId": 1,
            "Confidence": 99.44641876220703,
            "Geometry": {
                "BoundingBox": {
                    "Width": 0.029274433851242065,
                    "Height": 0.024024024605751038,
                    "Left": 0.4261065125465393,
                    "Top": 0.48848849534988403
                },
                "Polygon": [
                    {
                        "X": 0.4261065125465393,
                        "Y": 0.48848849534988403
                    },
                    {
                        "X": 0.45536383986473083,
                        "Y": 0.4874874949455261
                    },
                    {
                        "X": 0.45536383986473083,
                        "Y": 0.511511504650116
                    },
                    {
                        "X": 0.4261065125465393,
                        "Y": 0.5125125050544739
                    }
                ]
            }
        },
        {
            "DetectedText": "Freitag",
            "Type": "WORD",
            "Id": 7,
            "ParentId": 1,
            "Confidence": 99.44688415527344,
            "Geometry": {
                "BoundingBox": {
                    "Width": 0.06885894387960434,
                    "Height": 0.026123151183128357,
                    "Left": 0.45911478996276855,
                    "Top": 0.48948949575424194
                },
                "Polygon": [
                    {
                        "X": 0.45911478996276855,
                        "Y": 0.48948949575424194
                    },
                    {
                        "X": 0.5273818373680115,
                        "Y": 0.49849849939346313
                    },
                    {
                        "X": 0.5251312851905823,
                        "Y": 0.5245245099067688
                    },
                    {
                        "X": 0.45761439204216003,
                        "Y": 0.5155155062675476
                    }
                ]
            }
        },
        {
            "DetectedText": "10.00-18.30",
            "Type": "WORD",
            "Id": 8,
            "ParentId": 1,
            "Confidence": 95.54422760009766,
            "Geometry": {
                "BoundingBox": {
                    "Width": 0.11513171344995499,
                    "Height": 0.023071859031915665,
                    "Left": 0.5341335535049438,
                    "Top": 0.49849849939346313
                },
                "Polygon": [
                    {
                        "X": 0.5341335535049438,
                        "Y": 0.49849849939346313
                    },
                    {
                        "X": 0.648912250995636,
                        "Y": 0.5075075030326843
                    },
                    {
                        "X": 0.6474118232727051,
                        "Y": 0.5305305123329163
                    },
                    {
                        "X": 0.5333833694458008,
                        "Y": 0.5215215086936951
                    }
                ]
            }
        },
        {
            "DetectedText": "Uhr",
            "Type": "WORD",
            "Id": 9,
            "ParentId": 1,
            "Confidence": 95.97496032714844,
            "Geometry": {
                "BoundingBox": {
                    "Width": 0.039810311049222946,
                    "Height": 0.021021021530032158,
                    "Left": 0.649662435054779,
                    "Top": 0.5105105042457581
                },
                "Polygon": [
                    {
                        "X": 0.649662435054779,
                        "Y": 0.5105105042457581
                    },
                    {
                        "X": 0.6894223690032959,
                        "Y": 0.5125125050544739
                    },
                    {
                        "X": 0.6894223690032959,
                        "Y": 0.53353351354599
                    },
                    {
                        "X": 0.649662435054779,
                        "Y": 0.5305305123329163
                    }
                ]
            }
        },
        {
            "DetectedText": "Samstag",
            "Type": "WORD",
            "Id": 10,
            "ParentId": 2,
            "Confidence": 99.46641540527344,
            "Geometry": {
                "BoundingBox": {
                    "Width": 0.07717109471559525,
                    "Height": 0.025069961324334145,
                    "Left": 0.39759939908981323,
                    "Top": 0.5805805921554565
                },
                "Polygon": [
                    {
                        "X": 0.39759939908981323,
                        "Y": 0.5805805921554565
                    },
                    {
                        "X": 0.47411853075027466,
                        "Y": 0.5905905961990356
                    },
                    {
                        "X": 0.4726181626319885,
                        "Y": 0.6156156063079834
                    },
                    {
                        "X": 0.39684921503067017,
                        "Y": 0.6056056022644043
                    }
                ]
            }
        },
        {
            "DetectedText": "10.00",
            "Type": "WORD",
            "Id": 11,
            "ParentId": 2,
            "Confidence": 93.89275360107422,
            "Geometry": {
                "BoundingBox": {
                    "Width": 0.05349795147776604,
                    "Height": 0.019033808261156082,
                    "Left": 0.4778694808483124,
                    "Top": 0.5925925970077515
                },
                "Polygon": [
                    {
                        "X": 0.4778694808483124,
                        "Y": 0.5925925970077515
                    },
                    {
                        "X": 0.5311327576637268,
                        "Y": 0.597597599029541
                    },
                    {
                        "X": 0.5303825736045837,
                        "Y": 0.6166166067123413
                    },
                    {
                        "X": 0.4771192669868469,
                        "Y": 0.6116116046905518
                    }
                ]
            }
        },
        {
            "DetectedText": "17.00",
            "Type": "WORD",
            "Id": 12,
            "ParentId": 2,
            "Confidence": 91.7259750366211,
            "Geometry": {
                "BoundingBox": {
                    "Width": 0.054346393793821335,
                    "Height": 0.020076163113117218,
                    "Left": 0.5431357622146606,
                    "Top": 0.5985985994338989
                },
                "Polygon": [
                    {
                        "X": 0.5431357622146606,
                        "Y": 0.5985985994338989
                    },
                    {
                        "X": 0.5971493124961853,
                        "Y": 0.6046046018600464
                    },
                    {
                        "X": 0.5956488847732544,
                        "Y": 0.6246246099472046
                    },
                    {
                        "X": 0.5423855781555176,
                        "Y": 0.6186186075210571
                    }
                ]
            }
        },
        {
            "DetectedText": "Uhr",
            "Type": "WORD",
            "Id": 13,
            "ParentId": 2,
            "Confidence": 97.21809387207031,
            "Geometry": {
                "BoundingBox": {
                    "Width": 0.03697661682963371,
                    "Height": 0.019078107550740242,
                    "Left": 0.6009002327919006,
                    "Top": 0.6056056022644043
                },
                "Polygon": [
                    {
                        "X": 0.6009002327919006,
                        "Y": 0.6056056022644043
                    },
                    {
                        "X": 0.6376594305038452,
                        "Y": 0.6096096038818359
                    },
                    {
                        "X": 0.6361590623855591,
                        "Y": 0.6286286115646362
                    },
                    {
                        "X": 0.6001500487327576,
                        "Y": 0.6246246099472046
                    }
                ]
            }
        }
    ],
    "TextModelVersion": "3.0",
    "ResponseMetadata": {
        "RequestId": "9e6d54c3-eb3c-46a4-bd04-c96e30ef8f74",
        "HTTPStatusCode": 200,
        "HTTPHeaders": {
            "content-type": "application/x-amz-json-1.1",
            "date": "Sat, 10 Apr 2021 19:14:31 GMT",
            "x-amzn-requestid": "9e6d54c3-eb3c-46a4-bd04-c96e30ef8f74",
            "content-length": "6129",
            "connection": "keep-alive"
        },
        "RetryAttempts": 0
    }
}